{
  "status_standby": "● 待機中",
  "screen_this_window": "🖥 このウィンドウで開く",
  "screen_secondary": "⎇ セカンドモニターで全画面",
  "screen_primary_720": "☐ プライマリ 1280×720",
  "screen_primary_1080": "☐ プライマリ 1920×1080",
  "btn_reset": "リセット",
  "btn_apply_close": "適用して閉じる",
  "btn_copy": "コピー",
  "btn_refresh": "更新",
  "btn_apply": "適用",
  "btn_export": "エクスポート",
  "label_none": "選択なし",
  "label_remaining": "残り時間",
  "label_in": "IN（秒 / 0=カット）",
  "label_out": "OUT（秒 / 0=カット）",
  "label_sig_duration": "サイネージ時間（秒）",
  "editor_empty_title": "コンテンツを選択または新規作成",
  "drag_hint_main": "ここにドロップで一括登録",
  "drag_hint_sub": "画像・動画ファイルに対応",
  "bulk_zero_selected": "0件選択中",
  "btn_clear_select": "✕ 解除",
  "btn_bulk_delete": "🗑 一括削除",
  "cat_all": "すべて",
  "cat_media": "メディア",
  "cat_telop": "テロップ",
  "cat_break": "速報",
  "cat_scroll": "スクロール",
  "modal_new_title": "コンテンツタイプを選択",
  "type_telop_name": "テロップ",
  "type_telop_desc": "名前・肩書きの下部帯",
  "type_scroll_name": "スクロール",
  "type_scroll_desc": "横スクロールテキスト",
  "type_break_name": "速報",
  "type_break_desc": "中央大型速報テロップ",
  "type_media_name": "メディア",
  "type_media_desc": "画像・動画ポン出し",
  "type_slide_name": "スライド",
  "type_slide_desc": "複数メディアを順再生",
  "type_comp_name": "複合シーン",
  "type_comp_desc": "複数要素を同時表示",
  "label_content_name": "コンテンツ名",
  "btn_cancel": "キャンセル",
  "btn_create": "作成",
  "modal_del_title": "コンテンツを削除しますか?",
  "modal_del_msg": "この操作は元に戻せません。",
  "btn_delete": "削除",
  "editor_empty_msg": "右のリストからコンテンツを選択するか、<br>「新規作成」ボタンで追加してください",
  "placeholder_content_name": "例: 開幕テロップ",
  "scene_default": "シーン1",
  "scene_prefix": "シーン",
  "msg_select_content": "コンテンツを選択してください",
  "msg_scene_switch": "シーンを切り替えました: ",
  "msg_last_scene": "最後のシーンは削除できません",
  "notify_slides_uploading": "{0}個のファイルを追加中...",
  "notify_slides_added": "{0}個のファイルをスライドに追加しました",
  "notify_drop_files": "対応するファイルがありません",
  "notify_drop_n": "{0}件のファイルを一括登録中...",
  "notify_uploading": "アップロード中...",
  "notify_upload_done": "アップロード完了",
  "notify_url_fail": "ファイルURLの取得に失敗",
  "notify_upload_fail": "アップロードに失敗しました",
  "notify_json_applied": "JSONからコンテンツ一覧を適用しました",
  "notify_json_error": "JSONパースエラー: ",
  "notify_copy": "JSONをクリップボードにコピーしました",
  "notify_exported": "コンテンツ一覧をエクスポートしました",
  "notify_load_n": "ファイルから {0} 件のコンテンツを読み込みました",
  "notify_load_error": "ファイルの読み込みに失敗: ",
  "notify_duplicated": "コンテンツを複製しました",
  "notify_deleted": "コンテンツを削除しました",
  "notify_deleted_n": "{0}件のコンテンツを一度に削除しました",
  "notify_created": "作成しました",
  "btn_duplicate": "複製",
  "type_label_telop": "テロップ",
  "type_label_media": "メディア",
  "type_label_break": "速報",
  "type_label_scroll": "スクロール",
  "type_label_slide": "スライド",
  "type_label_comp": "複合",
  "summary_no_file": "ファイル未設定",
  "summary_slides": "スライド ({0}枚)",
  "summary_comp": "複合要素 ({0}個)",
  "bulk_selected": "{0}件選択中",
  "modal_del_title_n": "{0}件のコンテンツを削除しますか?",
  "unit_sec": "{0}秒",
  "unit_slides": "{0}枚",
  "pos_left": "左",
  "pos_center": "中央",
  "pos_right": "右",
  "lbl_name": "名前",
  "lbl_name_color": "名前色",
  "lbl_name_font": "名前フォント",
  "lbl_name_size": "名前サイズ",
  "lbl_title": "肩書き",
  "lbl_title_bg": "肩書き背景",
  "lbl_title_color": "肩書き色",
  "lbl_title_font": "肩書きフォント",
  "lbl_title_size": "肩書きサイズ",
  "lbl_bottom_px": "下端からの位置",
  "lbl_position": "左右位置",
  "lbl_accent": "アクセント色",
  "lbl_text": "テキスト",
  "lbl_text_color": "テキスト色",
  "lbl_text_font": "テキストフォント",
  "lbl_font_size": "フォントサイズ",
  "meta_enter": "IN:",
  "enter_cut": "カット",
  "enter_fade": "フェード",
  "meta_exit": "OUT:",
  "exit_cut": "カット",
  "exit_fade": "フェード",
  "meta_updated": "更新日時:",
  "meta_name": "名前:",
  "meta_title": "肩書き:",
  "meta_label": "ラベル:",
  "meta_speed": "速度:",
  "meta_kind": "種類:",
  "kind_video": "動画",
  "kind_image": "画像",
  "meta_slides_count": "枚数:",
  "meta_interval": "間隔:",
  "meta_elements": "要素数:"
}